{
  "locs": [
    [
      0.63,
      0.35
    ],
    [
      0.68,
      0.76
    ],
    [
      0.92,
      0.14
    ],
    [
      0.5,
      0.22
    ],
    [
      0.21,
      0.33
    ],
    [
      0.35,
      0.29
    ],
    [
      0.21,
      0.72
    ]
  ],
  "opt_value": 2.3714699745178223,
  "opt_count": 2,
  "feasible_count": 720,
  "mean_value": 3.2829325199127197,
  "std": 0.30092909932136536,
  "level": 2,
  "gammas": [
    -2.4076242446899414,
    -3.070255756378174
  ],
  "betas": [
    2.694371223449707,
    2.7170705795288086
  ],
  "predicted_p_opt": 0.06944444444444445,
  "predicted_tts": 14.399999999999999,
  "p_opt": 0.03910141438245773,
  "tts": 25.574522451255245,
  "approx": 1.3144582509994507,
  "opt_gap": 0.3144582509994507
}
