{
  "locs": [
    [
      0,
      0.91
    ],
    [
      0.6,
      0.1
    ],
    [
      0.8,
      0.95
    ],
    [
      0.95,
      0.37
    ],
    [
      0.52,
      0.8
    ],
    [
      0.88,
      0.72
    ],
    [
      0.45,
      0.03
    ],
    [
      0.08,
      0.92
    ],
    [
      0.6,
      0.92
    ],
    [
      0.92,
      0.27
    ]
  ],
  "opt_value": 3.1042680740356445,
  "opt_count": 2,
  "feasible_count": 362880,
  "mean_value": 6.3991241455078125,
  "std": 0.8008581399917603,
  "level": 3,
  "gammas": [
    -0.7444181442260742,
    -0.9566491842269897,
    -0.8982810974121094
  ],
  "betas": [
    2.9717352390289307,
    2.997525453567505,
    2.9371166229248047
  ],
  "predicted_p_opt": 0.0002700617283950617,
  "predicted_tts": 3702.857142857143,
  "p_opt": 0.0001965124101843685,
  "tts": 5088.737139103821,
  "approx": 1.9715802669525146,
  "opt_gap": 0.9715802669525146
}
