{
  "locs": [
    [
      0.62,
      0.77
    ],
    [
      0.12,
      0.28
    ],
    [
      0.91,
      0.54
    ],
    [
      0.59,
      0.81
    ],
    [
      0.72,
      0.76
    ],
    [
      0.8,
      0.53
    ],
    [
      0.75,
      0.32
    ],
    [
      0.76,
      0.48
    ],
    [
      0.11,
      0.89
    ],
    [
      0.35,
      0.28
    ],
    [
      0.56,
      0.88
    ],
    [
      0.5,
      0.92
    ]
  ],
  "opt_value": 2.557482957839966,
  "opt_count": 2,
  "feasible_count": 39916808,
  "mean_value": 5.3987040519714355,
  "std": 0.5590789914131165,
  "level": 3,
  "gammas": [
    -0.9221367239952087,
    -1.1321557760238647,
    -1.049551010131836
  ],
  "betas": [
    3.0019397735595703,
    3.0521717071533203,
    3.021167516708374
  ],
  "predicted_p_opt": 2.4551061297286094e-06,
  "predicted_tts": 407314.3673469388,
  "p_opt": 2.0298800791351823e-06,
  "tts": 492639.939806712,
  "approx": 2.089022159576416,
  "opt_gap": 1.089022159576416
}
